                 

# 1.背景介绍

编译原理是计算机科学的基础课程，它研究如何将高级语言的程序转换为计算机能够理解和执行的低级语言代码。编译器是将高级语言代码转换为低级语言代码的程序，而虚拟机是一种抽象的计算机，用于执行字节码。在这篇文章中，我们将从编译器到虚拟机的过程中探讨编译原理的核心概念、算法原理、具体操作步骤和数学模型。

# 2.核心概念与联系
编译原理的核心概念包括：

1. 语法分析：将程序按照语法规则划分为一系列的非终结符式。
2. 语义分析：分析程序的语义，确保程序的逻辑和语义正确。
3. 代码优化：提高程序的执行效率和空间效率。
4. 代码生成：将优化后的中间代码转换为目标代码。

编译器和虚拟机之间的关系如下：

1. 编译器将高级语言代码转换为低级语言代码（如机器代码或字节码）。
2. 虚拟机将字节码转换为计算机能够执行的机器代码。

# 3.核心算法原理和具体操作步骤以及数学模型公式详细讲解
## 3.1 语法分析
语法分析的主要算法有：

1. 先行检查（Parse-time Check）：在编译过程中，根据语法规则检查程序的语法正确性。
2. 递归下降（Recursive Descent）：将语法规则转换为递归的函数调用，逐步解析程序。
3. 表达式解析（Expression Parsing）：将表达式按照优先级和结合律解析。

数学模型公式：

$$
G = (V, T, P, S)
$$

其中，$G$ 是语法规则的集合，$V$ 是非终结符集合，$T$ 是终结符集合，$P$ 是产生式集合，$S$ 是起始符。

## 3.2 语义分析
语义分析的主要算法有：

1. 类型检查（Type Checking）：确保程序中的类型匹配，避免类型错误。
2. 变量声明检查（Variable Declaration Check）：确保所有变量都有正确的声明。
3. 控制流分析（Control Flow Analysis）：分析程序的控制流，确保程序的逻辑正确。

数学模型公式：

$$
\phi : V \rightarrow T^*
$$

其中，$\phi$ 是语义函数，$V$ 是非终结符集合，$T^*$ 是终结符的星集合。

## 3.3 代码优化
代码优化的主要算法有：

1. 常量折叠（Constant Folding）：将表达式中的常量计算并替换。
2. 死代码消除（Dead Code Elimination）：删除不会被执行的代码。
3. 循环不变量分析（Loop Invariant Analysis）：分析循环中的不变量，将其提升到循环外。

数学模型公式：

$$
O(n) = (C, F)
$$

其中，$O(n)$ 是优化后的代码，$C$ 是控制流，$F$ 是函数集合。

## 3.4 代码生成
代码生成的主要算法有：

1. 中间代码生成（Intermediate Code Generation）：将优化后的中间代码转换为目标代码。
2. 机器代码生成（Machine Code Generation）：将中间代码或直接高级语言代码转换为机器代码。
3. 字节码生成（Bytecode Generation）：将高级语言代码转换为虚拟机可执行的字节码。

数学模型公式：

$$
G'(n) = (C', F')
$$

其中，$G'(n)$ 是优化后的代码，$C'$ 是优化后的控制流，$F'$ 是优化后的函数集合。

# 4.具体代码实例和详细解释说明
在这里，我们以一个简单的计算器程序为例，展示编译器和虚拟机的代码生成过程。

## 4.1 编译器生成机器代码
```c
#include <stdio.h>

int add(int a, int b) {
    return a + b;
}

int main() {
    int x = 10;
    int y = 20;
    int z = add(x, y);
    printf("x + y = %d\n", z);
    return 0;
}
```
这个程序定义了一个 `add` 函数，将两个整数相加，并在 `main` 函数中调用该函数。编译器将生成如下机器代码：

```assembly
main:
    mov eax, 10    ; 加载 x 的值
    mov ebx, 20    ; 加载 y 的值
    call add       ; 调用 add 函数
    add eax, ebx   ; 将结果存储在 eax 中
    push eax       ; 将结果推入堆栈
    push 10        ; 推入 x 的值
    push 20        ; 推入 y 的值
    call printf    ; 调用 printf 函数
    add esp, 12    ; 清理堆栈
    ret

add:
    add eax, ebx   ; 将 a 和 b 相加，结果存储在 eax 中
    mov esp, ebp   ; 清理堆栈
    pop ebp        ; 恢复调用者的堆栈帧
    ret
```
## 4.2 虚拟机生成字节码
```java
public class Calculator {
    public static int add(int a, int b) {
        return a + b;
    }

    public static void main(String[] args) {
        int x = 10;
        int y = 20;
        int z = add(x, y);
        System.out.println("x + y = " + z);
    }
}
```
这个程序定义了一个 `add` 函数，将两个整数相加，并在 `main` 函数中调用该函数。虚拟机将生成如下字节码：

```
0: iload_0    ; 加载 x 的值
2: iload_1    ; 加载 y 的值
4: iadd        ; 将 a 和 b 相加
6: istore_2    ; 将结果存储在 z 中
8: getstatic    #2                  // Field java/lang/System.out:Ljava/io/PrintStream;
11: ldc         #3                  // String x + y = %d
13: iload_2     ; 加载 z 的值
14: invokestatic #4                  // Method java/lang/String.format:(Ljava/util/Locale;Ljava/lang/String;[Ljava/lang/Object;)Ljava/lang/String;
   17: invokevirtual   #5                 // Method java/io/PrintStream.println:(Ljava/lang/Object;)V
   20: return
```
# 5.未来发展趋势与挑战
编译原理和虚拟机的未来发展趋势包括：

1. 多核和并行计算：随着硬件技术的发展，编译器和虚拟机需要更好地支持多核和并行计算，以提高程序的执行效率。
2. 自动化优化：编译器和虚拟机需要进行更多的自动化优化，以提高程序的性能和空间效率。
3. 安全性和隐私：编译器和虚拟机需要更好地保护程序和数据的安全性和隐私，以防止恶意代码和数据泄露。
4. 跨平台和跨语言：编译器和虚拟机需要支持更多的平台和编程语言，以满足不同应用的需求。

挑战包括：

1. 性能优化：如何在保证程序正确性的同时，提高编译器和虚拟机的性能，是一个重要的挑战。
2. 兼容性：如何保证编译器和虚拟机对于不同的平台和编程语言的兼容性，是一个难题。
3. 安全性：如何在编译过程中检测和防止恶意代码和数据泄露，是一个重要的安全挑战。

# 6.附录常见问题与解答
Q: 编译器和虚拟机有哪些不同？
A: 编译器将高级语言代码转换为低级语言代码（如机器代码），而虚拟机将字节码转换为计算机能够执行的机器代码。编译器通常针对特定的目标平台进行优化，而虚拟机可以在不同平台上运行相同的字节码。

Q: 如何提高编译器和虚拟机的性能？
A: 可以通过优化算法、使用更高效的数据结构和算法，以及更好地利用硬件资源（如缓存和并行计算）来提高编译器和虚拟机的性能。

Q: 如何保证编译器和虚拟机的兼容性？
A: 可以通过使用通用的接口和抽象层，以及支持多平台和多语言来保证编译器和虚拟机的兼容性。

Q: 如何保证编译器和虚拟机的安全性？
A: 可以通过静态和动态分析代码，检测恶意代码和数据泄露，以及使用安全的编译和执行技术来保证编译器和虚拟机的安全性。