# -Python：高效开发语言

## 1.背景介绍

Python是一种广泛使用的高级编程语言,它的设计理念强调代码的可读性和简洁性。Python最初是由吉多·范罗苏姆在1991年设计出来的,目的是作为一种能够以简单的方式完成系统脚本工作的语言。如今,Python已经发展成为一种通用编程语言,被广泛应用于网络开发、数据分析、人工智能等多个领域。

Python的主要特点包括:

1. **简单易学**: Python语法简单清晰,阅读性强,初学者很容易上手。
2. **开源免费**: Python及其庞大的生态库都是开源免费的,这降低了学习和使用的门槛。
3. **可移植性强**: Python遵循跨平台的设计理念,代码可以在Windows、Linux和macOS等多种系统上运行。
4. **面向对象**: Python全面支持面向对象编程,并集成了一些函数式编程的特性。
5. **丰富的库**: Python拥有数以万计的第三方库,涵盖了从Web开发、数据处理到科学计算等各个领域。
6. **动态类型**: Python是动态类型语言,变量无需预先声明类型,这增加了编程的灵活性。

凭借这些优势,Python已成为当今最流行的编程语言之一,被广泛应用于科学计算、Web开发、系统运维、机器学习等领域。

## 2.核心概念与联系

### 2.1 Python解释器

Python是一种解释型语言,代码需要通过Python解释器来执行。解释器的作用是将源代码一行一行地解释成特定的机器指令,然后由计算机执行。这与编译型语言不同,编译型语言需要先将整个源代码编译成机器码,然后再执行。

Python有两种主要的解释器实现:CPython和PyPy。CPython是使用C语言编写的Python参考实现,它是最常用的Python解释器。PyPy则是Python的一种替代实现,它采用Just-In-Time(JIT)编译技术,在特定场景下可以比CPython更高效。

### 2.2 动态类型

Python是动态类型语言,这意味着变量的类型在运行时确定,而不是在编译时确定。这为编程带来了极大的灵活性,但也可能导致一些类型相关的错误。Python解释器会在运行时自动推断变量的类型,并根据需要进行隐式类型转换。

```python
x = 5       # x是整数
x = "Hello" # x现在是字符串
```

动态类型使得Python代码更加简洁,但也需要程序员更加小心谨慎,避免出现类型相关的错误。

### 2.3 面向对象编程

Python全面支持面向对象编程范式。在Python中,一切皆对象,包括类、函数、模块等。Python的面向对象特性借鉴了C++和Java等语言,但又有自己的一些独特之处,比如多重继承、属性访问方法等。

```python
class Person:
    def __init__(self, name, age):
        self.name = name
        self.age = age

    def greet(self):
        print(f"Hello, my name is {self.name}")

person = Person("Alice", 25)
person.greet() # 输出: Hello, my name is Alice
```

Python的面向对象特性使得代码更加模块化、可重用和可扩展。

### 2.4 函数式编程

除了面向对象编程,Python还支持函数式编程范式。函数在Python中是一等公民,可以作为参数传递给其他函数,也可以作为返回值返回。Python还内置了许多函数式编程的特性,如lambda表达式、列表推导式、生成器等。

```python
numbers = [1, 2, 3, 4, 5]
squared = list(map(lambda x: x**2, numbers))
# squared is [1, 4, 9, 16, 25]
```

函数式编程有助于编写更加简洁、可读和可组合的代码。

### 2.5 Python生态系统

Python拥有一个庞大的生态系统,包括数以万计的第三方库和框架。这些库涵盖了从Web开发、数据处理到科学计算等各个领域。著名的Python库包括NumPy(科学计算)、Pandas(数据分析)、Django(Web开发)、TensorFlow(机器学习)等。

Python的包管理工具pip使得安装和管理第三方库变得非常简单。强大的生态系统是Python作为通用编程语言的重要原因之一。

## 3.核心算法原理具体操作步骤  

### 3.1 Python解释器工作原理

Python解释器的工作原理可以概括为以下几个步骤:

1. **词法分析(Lexing)**: 将源代码分解成一个个token(如关键字、标识符、运算符等)的过程。
2. **语法分析(Parsing)**: 根据Python语法规则,将token序列构建成抽象语法树(Abstract Syntax Tree, AST)的过程。
3. **编译(Compiling)**: 将AST编译成字节码(Bytecode)的过程。字节码是Python虚拟机(PVM)可以直接执行的低级指令序列。
4. **执行(Executing)**: Python虚拟机执行字节码,完成相应的计算和操作。

以下是一个简单的Python代码及其对应的字节码:

```python
x = 1
y = 2
z = x + y
print(z)
```

对应的字节码:

```
  1           0 LOAD_CONST               0 (1)
              2 STORE_NAME               0 (x)

  2           4 LOAD_CONST               1 (2)
              6 STORE_NAME               1 (y)

  3           8 LOAD_NAME                0 (x)
             10 LOAD_NAME                1 (y)
             12 BINARY_ADD
             14 STORE_NAME               2 (z)

  4          16 LOAD_NAME                2 (z)
             18 CALL_FUNCTION            0
             20 PRINT_EXPR
             22 LOAD_CONST               2 (None)
             24 RETURN_VALUE
```

Python解释器的工作方式使得Python代码可以在多种平台上运行,但也导致了一定的性能损失。为了提高性能,Python社区开发了多种优化技术,如PyPy的JIT编译、Numba等。

### 3.2 Python内存管理

Python使用了自动内存管理机制,程序员无需手动分配和释放内存。Python的内存管理主要依赖于引用计数和分代回收两种机制。

1. **引用计数(Reference Counting)**: Python为每个对象维护一个引用计数,当引用计数为0时,该对象所占用的内存将被自动回收。
2. **分代回收(Generational Garbage Collection)**: Python将对象根据其存活时间划分为不同的代,对不同代的对象采用不同的回收策略。新创建的对象被放入第0代,如果它们在下一次垃圾回收时仍然存活,就会被移动到下一代。

引用计数机制简单高效,但无法解决循环引用的问题。分代回收则可以有效解决这个问题,但代价是需要暂停程序执行,进行全局扫描。Python在运行时自动选择合适的回收策略。

### 3.3 Python虚拟机

Python虚拟机(PVM)是Python解释器的核心组件,它负责执行Python字节码。PVM是一个栈式虚拟机,它维护了一个用于存储数据和指令的主栈。

在执行字节码时,PVM会根据当前指令从栈中取出操作数,执行相应的操作,并将结果压回栈中。例如,对于字节码`BINARY_ADD`,PVM会从栈中弹出两个操作数,执行加法运算,然后将结果压回栈中。

PVM还负责管理Python的内存、异常处理、线程调度等功能。它是Python解释器的执行引擎,对Python的性能有着重要影响。

## 4.数学模型和公式详细讲解举例说明

在Python中,我们可以使用NumPy和SymPy等库来处理数学模型和公式。NumPy专注于科学计算,而SymPy则侧重于符号计算。

### 4.1 NumPy

NumPy(Numerical Python)是Python中最著名的科学计算库之一。它提供了高性能的多维数组对象,以及对数组进行运算的函数。NumPy的核心是ndarray对象,它是一个同质的多维数组,可以存储任何数据类型。

NumPy中的数组运算是向量化的,这意味着操作可以同时应用于整个数组,而不需要使用显式循环。这种向量化操作通常比纯Python代码快得多。

以下是一些NumPy的基本用法:

```python
import numpy as np

# 创建一个一维数组
a = np.array([1, 2, 3, 4])

# 创建一个二维数组
b = np.array([[1, 2], [3, 4]])

# 数组运算
c = a + b  # 对应元素相加
d = np.dot(a, b.T)  # 矩阵乘法

# 数学函数
e = np.sin(a)  # 对数组中每个元素应用sin函数
```

NumPy还提供了许多用于线性代数、随机数生成、傅里叶变换等的函数和模块。它是Python中进行科学计算的基础库。

### 4.2 SymPy

SymPy(Symbolic Python)是一个用于符号数学的Python库。它可以进行符号计算、简化表达式、求解方程、微分和积分等操作。

SymPy中的核心对象是`Symbol`和`Expr`。`Symbol`表示一个符号变量,而`Expr`则表示一个数学表达式。

以下是一些SymPy的基本用法:

```python
import sympy as sp

# 创建符号变量
x, y = sp.symbols('x y')

# 创建表达式
expr = x**2 + 2*x*y + y**2

# 简化表达式
simplified = expr.simplify()  # (x + y)**2

# 求导
derivative = expr.diff(x)  # 2*x + 2*y

# 求解方程
equation = sp.Eq(x**2 + 2*x - 3, 0)
solutions = sp.solveset(equation, x)  # {-3, 1}
```

SymPy还支持矩阵运算、微分方程求解、拉普拉斯变换等高级数学运算。它是Python中进行符号计算的重要工具。

### 4.3 数学公式示例

以下是一个使用LaTeX格式表示的数学公式示例,描述了线性回归模型:

$$
y = \theta_0 + \theta_1 x_1 + \theta_2 x_2 + \cdots + \theta_n x_n
$$

其中:

- $y$是因变量(目标变量)
- $x_1, x_2, \ldots, x_n$是自变量(特征变量)
- $\theta_0, \theta_1, \ldots, \theta_n$是模型参数(权重)

线性回归的目标是找到一组最优参数$\theta$,使得模型对训练数据的预测值与真实值之间的均方误差最小化:

$$
J(\theta) = \frac{1}{2m} \sum_{i=1}^m (h_\theta(x^{(i)}) - y^{(i)})^2
$$

其中:

- $m$是训练样本数量
- $h_\theta(x^{(i)})$是模型对第$i$个样本的预测值
- $y^{(i)}$是第$i$个样本的真实值

我们可以使用梯度下降法来求解最优参数$\theta$:

$$
\theta_j := \theta_j - \alpha \frac{\partial}{\partial \theta_j} J(\theta)
$$

其中$\alpha$是学习率(步长),决定了每次迭代的步伐大小。

通过NumPy和SymPy,我们可以在Python中方便地实现和操作这些数学模型和公式。

## 5.项目实践:代码实例和详细解释说明

在这一部分,我们将通过一个实际项目来展示如何使用Python进行数据分析和机器学习建模。我们将使用著名的鸢尾花数据集(Iris Dataset)作为示例。

### 5.1 数据集介绍

鸢尾花数据集是一个常用的机器学习示例数据集,由150个样本组成,每个样本包含4个特征(花萼长度、花萼宽度、花瓣长度、花瓣宽度)和1个类别标签(鸢尾花品种)。数据集中的3个类别分别是山鸢尾、杂色鸢尾和维吉尼亚鸢尾。

我们将使用Python的数据分析库Pandas和机器学习库Scikit-learn来处理这个数据集。

### 5.2 数据加载和探索

首先,我们需要导入所需的库并加载数据集:

```python
import pandas as pd
from sklearn.datasets import load_iris

# 加载